MANIFEST.in
setup.py
HSI.egg-info/PKG-INFO
HSI.egg-info/SOURCES.txt
HSI.egg-info/dependency_links.txt
HSI.egg-info/not-zip-safe
HSI.egg-info/requires.txt
HSI.egg-info/top_level.txt
src/.hsimage.h.swp
src/HSI.dxy
src/HSImage.pro
src/HSImage.pro.user
src/annEnums.h
src/classifiedhsimage.cpp
src/classifiedhsimage.h
src/colormap.cpp
src/colormap.h
src/hsimage.cpp
src/hsimage.h
src/hsimage.h.autosave
src/hsimage_global.h
src/labelfile.cpp
src/labelfile.h
src/main.cpp
src/pyboost_cv3_converter.cpp
src/python_utils.cpp
src/python_utils.h
src/target.cpp
src/target.h
src/test.txt
src/jsoncpp/jsoncpp.cpp
src/jsoncpp/json/json-forwards.h
src/jsoncpp/json/json.h
src/pybind11_opencv_numpy/.gitignore
src/pybind11_opencv_numpy/__init__.py
src/pybind11_opencv_numpy/example.cpp
src/pybind11_opencv_numpy/ndarray_converter.cpp
src/pybind11_opencv_numpy/ndarray_converter.h
src/pybind11_opencv_numpy/setup.py
src/pybind11_opencv_numpy/test.png
src/pybind11_opencv_numpy/test.py
src/pybind11_opencv_numpy/.git/HEAD
src/pybind11_opencv_numpy/.git/config
src/pybind11_opencv_numpy/.git/description
src/pybind11_opencv_numpy/.git/index
src/pybind11_opencv_numpy/.git/packed-refs
src/pybind11_opencv_numpy/.git/hooks/applypatch-msg.sample
src/pybind11_opencv_numpy/.git/hooks/commit-msg.sample
src/pybind11_opencv_numpy/.git/hooks/post-update.sample
src/pybind11_opencv_numpy/.git/hooks/pre-applypatch.sample
src/pybind11_opencv_numpy/.git/hooks/pre-commit.sample
src/pybind11_opencv_numpy/.git/hooks/pre-push.sample
src/pybind11_opencv_numpy/.git/hooks/pre-rebase.sample
src/pybind11_opencv_numpy/.git/hooks/prepare-commit-msg.sample
src/pybind11_opencv_numpy/.git/hooks/update.sample
src/pybind11_opencv_numpy/.git/info/exclude
src/pybind11_opencv_numpy/.git/logs/HEAD
src/pybind11_opencv_numpy/.git/logs/refs/heads/master
src/pybind11_opencv_numpy/.git/logs/refs/remotes/origin/HEAD
src/pybind11_opencv_numpy/.git/objects/00/47874db85b81e106c20c19b4d3da7a62170a44
src/pybind11_opencv_numpy/.git/objects/01/8e1ee778976db9c0aabf07f486d7e893798378
src/pybind11_opencv_numpy/.git/objects/03/a2b05adecb67d7d877b5eacd57fe749351ed2f
