Metadata-Version: 1.2
Name: HSI
Version: 1.2.1
Summary: Interactivity class for hyperspectral ENVI-BIL images
Home-page: https://osf.io/b5t3x
Author: Ryan Brown
Author-email: brownrc@vt.edu
License: MIT
Download-URL: https://github.com/dtchuck/HSImage/archive/0.1.targ.gz
Keywords: hyperspectral,image,interface
Platform: UNKNOWN
Classifier: Development Status :: 4 - Beta
Classifier: Intended Audience :: Science/Research
Classifier: Topic :: Scientific/Engineering :: Image Recognition
Classifier: License :: OSI Approved :: MIT License
Classifier: Programming Language :: Python :: 3 :: Only
Requires-Python: >=2.7,!=3.0.*,!=3.1.*
